<?xml version="1.0" encoding="utf-8" ?>
<dwsync>
<file name="athletics.png" server="chrisvwebb.com//school/imd-495/app/" local="3467122644" remote="319519907859930340" Dst="-1" />
<file name="bg.jpg" server="chrisvwebb.com//school/imd-495/app/" local="3467121287" remote="319519907859930340" Dst="-1" />
<file name="login.png" server="chrisvwebb.com//school/imd-495/app/" local="3467122646" remote="319519907859930340" Dst="-1" />
<file name="activities.png" server="chrisvwebb.com//school/imd-495/app/" local="3467132947" remote="319519907859939460" Dst="-1" />
<file name="header.png" server="chrisvwebb.com//school/imd-495/app/" local="3467132964" remote="319519907859939460" Dst="-1" />
<file name="submit.png" server="chrisvwebb.com//school/imd-495/app/" local="3467132948" remote="319519907859939460" Dst="-1" />
<file name="clarkscorner2.png" server="chrisvwebb.com//school/imd-495/app/" local="3467132947" remote="319519907859939700" Dst="-1" />
<file name="newsfeed2.png" server="chrisvwebb.com//school/imd-495/app/" local="3467132947" remote="319519907859939700" Dst="-1" />
<file name="schoolinfo2.png" server="chrisvwebb.com//school/imd-495/app/" local="3467132948" remote="319519907859939700" Dst="-1" />
<file name="teachers2.png" server="chrisvwebb.com//school/imd-495/app/" local="3467132947" remote="319519907859939700" Dst="-1" />
<file name="welcome2.png" server="chrisvwebb.com//school/imd-495/app/" local="3467133649" remote="319519907859940060" Dst="-1" />
<file name="welcome3.png" server="chrisvwebb.com//school/imd-495/app/" local="3467133712" remote="319519907859940120" Dst="-1" />
<file name="activities-header.jpg" server="chrisvwebb.com//school/imd-495/app/" local="3468347074" remote="319519907861153740" Dst="-1" />
<file name="clarks-header.jpg" server="chrisvwebb.com//school/imd-495/app/" local="3468348049" remote="319519907861154460" Dst="-1" />
<file name="school-header.jpg" server="chrisvwebb.com//school/imd-495/app/" local="3468348062" remote="319519907861154460" Dst="-1" />
<file name="teachers-header.jpg" server="chrisvwebb.com//school/imd-495/app/" local="3468347611" remote="319519907861154220" Dst="-1" />
<file name="activities-header.jpg" server="imd495.alexsablan.info/imd495.alexsablan.info/projects/" local="130304070970910817" remote="130303965000000000" Dst="1" />
<file name="athletics.png" server="imd495.alexsablan.info/imd495.alexsablan.info/projects/" local="130304070972540890" remote="130303965000000000" Dst="1" />
<file name="bg.jpg" server="imd495.alexsablan.info/imd495.alexsablan.info/projects/" local="130304070973250933" remote="130303965000000000" Dst="1" />
<file name="btm-activities.png" server="imd495.alexsablan.info/imd495.alexsablan.info/projects/" local="130304070973710958" remote="130303965000000000" Dst="1" />
<file name="activities.png" server="imd495.alexsablan.info/imd495.alexsablan.info/projects/" local="130304070971780844" remote="130303965000000000" Dst="1" />
<file name="btm-home.png" server="imd495.alexsablan.info/imd495.alexsablan.info/projects/" local="130304070974110981" remote="130303965000000000" Dst="1" />
<file name="btm-principal-clark.png" server="imd495.alexsablan.info/imd495.alexsablan.info/projects/" local="130304070974470999" remote="130303965000000000" Dst="1" />
<file name="btm-school.png" server="imd495.alexsablan.info/imd495.alexsablan.info/projects/" local="130304070975131034" remote="130303965000000000" Dst="1" />
<file name="btm-teachers.png" server="imd495.alexsablan.info/imd495.alexsablan.info/projects/" local="130304070975461053" remote="130303965000000000" Dst="1" />
<file name="clarkscorner2.png" server="imd495.alexsablan.info/imd495.alexsablan.info/projects/" local="130304070976281111" remote="130303965000000000" Dst="1" />
<file name="clarks-header.jpg" server="imd495.alexsablan.info/imd495.alexsablan.info/projects/" local="130304070975771072" remote="130303965000000000" Dst="1" />
<file name="header.png" server="imd495.alexsablan.info/imd495.alexsablan.info/projects/" local="130304070976851136" remote="130303965000000000" Dst="1" />
<file name="login.png" server="imd495.alexsablan.info/imd495.alexsablan.info/projects/" local="130304070977231154" remote="130303965000000000" Dst="1" />
<file name="page-img.png" server="imd495.alexsablan.info/imd495.alexsablan.info/projects/" local="130304070978131233" remote="130303965000000000" Dst="1" />
<file name="school-header.jpg" server="imd495.alexsablan.info/imd495.alexsablan.info/projects/" local="130304070978401241" remote="130303965000000000" Dst="1" />
<file name="newsfeed2.png" server="imd495.alexsablan.info/imd495.alexsablan.info/projects/" local="130304070977731194" remote="130303965000000000" Dst="1" />
<file name="schoolinfo2.png" server="imd495.alexsablan.info/imd495.alexsablan.info/projects/" local="130304070978921253" remote="130303965000000000" Dst="1" />
<file name="submit.png" server="imd495.alexsablan.info/imd495.alexsablan.info/projects/" local="130304070979551289" remote="130303965000000000" Dst="1" />
<file name="teachers-header.jpg" server="imd495.alexsablan.info/imd495.alexsablan.info/projects/" local="130304070979911307" remote="130303965000000000" Dst="1" />
<file name="teachers2.png" server="imd495.alexsablan.info/imd495.alexsablan.info/projects/" local="130304070981471400" remote="130303965000000000" Dst="1" />
<file name="welcome2.png" server="imd495.alexsablan.info/imd495.alexsablan.info/projects/" local="130304070982141437" remote="130303965000000000" Dst="1" />
<file name="welcome3.png" server="imd495.alexsablan.info/imd495.alexsablan.info/projects/" local="130304070982641468" remote="130303965000000000" Dst="1" />
</dwsync>